{
  "boundaries": [
    {
      "vertices": [
        {
          "x": 1.0,
          "y": 0.0,
          "z": 0.0
        },
        {
          "x": 1.0,
          "y": 1.0,
          "z": 0.0
        },
        {
          "x": 1.0,
          "y": 1.0,
          "z": 1.0
        },
        {
          "x": 1.0,
          "y": 0.0,
          "z": 1.0
        },
        {
          "x": 0.0,
          "y": 0.0,
          "z": 1.0
        },
        {
          "x": 0.0,
          "y": 1.0,
          "z": 1.0
        },
        {
          "x": 0.5,
          "y": 0.75,
          "z": 1.0
        },
        {
          "x": 0.5,
          "y": 0.25,
          "z": 1.0
        },
        {
          "x": 0.5,
          "y": 0.75,
          "z": 0.0
        },
        {
          "x": 0.5,
          "y": 0.25,
          "z": 0.0
        },
        {
          "x": 0.0,
          "y": 0.0,
          "z": 0.0
        },
        {
          "x": 0.0,
          "y": 1.0,
          "z": 0.0
        }
      ],
      "edges": [
        {
          "vertices": [
            0,
            1
          ],
          "curve": {
            "Line": [
              {
                "x": 1.0,
                "y": 0.0,
                "z": 0.0
              },
              {
                "x": 1.0,
                "y": 1.0,
                "z": 0.0
              }
            ]
          }
        },
        {
          "vertices": [
            1,
            2
          ],
          "curve": {
            "Line": [
              {
                "x": 1.0,
                "y": 1.0,
                "z": 0.0
              },
              {
                "x": 1.0,
                "y": 1.0,
                "z": 1.0
              }
            ]
          }
        },
        {
          "vertices": [
            3,
            2
          ],
          "curve": {
            "Line": [
              {
                "x": 1.0,
                "y": 0.0,
                "z": 1.0
              },
              {
                "x": 1.0,
                "y": 1.0,
                "z": 1.0
              }
            ]
          }
        },
        {
          "vertices": [
            0,
            3
          ],
          "curve": {
            "Line": [
              {
                "x": 1.0,
                "y": 0.0,
                "z": 0.0
              },
              {
                "x": 1.0,
                "y": 0.0,
                "z": 1.0
              }
            ]
          }
        },
        {
          "vertices": [
            4,
            3
          ],
          "curve": {
            "Line": [
              {
                "x": 0.0,
                "y": 0.0,
                "z": 1.0
              },
              {
                "x": 1.0,
                "y": 0.0,
                "z": 1.0
              }
            ]
          }
        },
        {
          "vertices": [
            5,
            2
          ],
          "curve": {
            "Line": [
              {
                "x": 0.0,
                "y": 1.0,
                "z": 1.0
              },
              {
                "x": 1.0,
                "y": 1.0,
                "z": 1.0
              }
            ]
          }
        },
        {
          "vertices": [
            4,
            5
          ],
          "curve": {
            "Line": [
              {
                "x": 0.0,
                "y": 0.0,
                "z": 1.0
              },
              {
                "x": 0.0,
                "y": 1.0,
                "z": 1.0
              }
            ]
          }
        },
        {
          "vertices": [
            6,
            7
          ],
          "curve": {
            "IntersectionCurve": {
              "surface0": {
                "Plane": {
                  "o": {
                    "x": 0.0,
                    "y": 0.0,
                    "z": 1.0
                  },
                  "p": {
                    "x": 1.0,
                    "y": 0.0,
                    "z": 1.0
                  },
                  "q": {
                    "x": 0.0,
                    "y": 1.0,
                    "z": 1.0
                  }
                }
              },
              "surface1": {
                "NURBSSurface": {
                  "knot_vecs": [
                    [
                      0.0,
                      0.0,
                      0.0,
                      0.25,
                      0.5,
                      0.75,
                      1.0,
                      1.0,
                      1.0
                    ],
                    [
                      0.0,
                      0.0,
                      1.0,
                      1.0
                    ]
                  ],
                  "control_points": [
                    [
                      {
                        "x": 0.5,
                        "y": 0.25,
                        "z": -0.5,
                        "w": 1.0
                      },
                      {
                        "x": 0.5,
                        "y": 0.25,
                        "z": 1.5,
                        "w": 1.0
                      }
                    ],
                    [
                      {
                        "x": 0.4375,
                        "y": 0.1875,
                        "z": -0.375,
                        "w": 0.75
                      },
                      {
                        "x": 0.4375,
                        "y": 0.1875,
                        "z": 1.125,
                        "w": 0.75
                      }
                    ],
                    [
                      {
                        "x": 0.375,
                        "y": 0.1875,
                        "z": -0.25,
                        "w": 0.5
                      },
                      {
                        "x": 0.375,
                        "y": 0.1875,
                        "z": 0.75,
                        "w": 0.5
                      }
                    ],
                    [
                      {
                        "x": 0.375,
                        "y": 0.31249999999999994,
                        "z": -0.25,
                        "w": 0.5
                      },
                      {
                        "x": 0.375,
                        "y": 0.31249999999999994,
                        "z": 0.75,
                        "w": 0.5
                      }
                    ],
                    [
                      {
                        "x": 0.4375,
                        "y": 0.5625,
                        "z": -0.375,
                        "w": 0.75
                      },
                      {
                        "x": 0.4375,
                        "y": 0.5625,
                        "z": 1.125,
                        "w": 0.75
                      }
                    ],
                    [
                      {
                        "x": 0.5,
                        "y": 0.75,
                        "z": -0.5,
                        "w": 1.0
                      },
                      {
                        "x": 0.5,
                        "y": 0.75,
                        "z": 1.5,
                        "w": 1.0
                      }
                    ]
                  ]
                }
              },
              "leader": {
                "Polyline": [
                  {
                    "x": 0.5,
                    "y": 0.75,
                    "z": 1.0
                  },
                  {
                    "x": 0.5353553390593275,
                    "y": 0.7474873734152929,
                    "z": 1.0
                  },
                  {
                    "x": 0.5469827033686665,
                    "y": 0.7455455902473329,
                    "z": 1.0
                  },
                  {
                    "x": 0.57,
                    "y": 0.74,
                    "z": 1.0
                  },
                  {
                    "x": 0.65,
                    "y": 0.7,
                    "z": 1.0
                  },
                  {
                    "x": 0.6770612931366362,
                    "y": 0.67649209741382,
                    "z": 1.0
                  },
                  {
                    "x": 0.7205882352941176,
                    "y": 0.6176470588235294,
                    "z": 1.0
                  },
                  {
                    "x": 0.75,
                    "y": 0.4999999999999999,
                    "z": 1.0
                  },
                  {
                    "x": 0.7205882352941176,
                    "y": 0.3823529411764708,
                    "z": 1.0
                  },
                  {
                    "x": 0.6500000000000001,
                    "y": 0.30000000000000016,
                    "z": 1.0
                  },
                  {
                    "x": 0.5700000000000001,
                    "y": 0.26000000000000006,
                    "z": 1.0
                  },
                  {
                    "x": 0.5469827033686666,
                    "y": 0.2544544097526669,
                    "z": 1.0
                  },
                  {
                    "x": 0.5353553390593275,
                    "y": 0.252512626584707,
                    "z": 1.0
                  },
                  {
                    "x": 0.5,
                    "y": 0.25,
                    "z": 1.0
                  }
                ]
              },
              "tol": 0.01
            }
          }
        },
        {
          "vertices": [
            6,
            7
          ],
          "curve": {
            "IntersectionCurve": {
              "surface0": {
                "Plane": {
                  "o": {
                    "x": 0.0,
                    "y": 0.0,
                    "z": 1.0
                  },
                  "p": {
                    "x": 1.0,
                    "y": 0.0,
                    "z": 1.0
                  },
                  "q": {
                    "x": 0.0,
                    "y": 1.0,
                    "z": 1.0
                  }
                }
              },
              "surface1": {
                "NURBSSurface": {
                  "knot_vecs": [
                    [
                      0.0,
                      0.0,
                      0.0,
                      0.25,
                      0.5,
                      0.75,
                      1.0,
                      1.0,
                      1.0
                    ],
                    [
                      0.0,
                      0.0,
                      1.0,
                      1.0
                    ]
                  ],
                  "control_points": [
                    [
                      {
                        "x": 0.5,
                        "y": 0.75,
                        "z": -0.5,
                        "w": 1.0
                      },
                      {
                        "x": 0.5,
                        "y": 0.75,
                        "z": 1.5,
                        "w": 1.0
                      }
                    ],
                    [
                      {
                        "x": 0.3125,
                        "y": 0.5625,
                        "z": -0.375,
                        "w": 0.75
                      },
                      {
                        "x": 0.3125,
                        "y": 0.5625,
                        "z": 1.125,
                        "w": 0.75
                      }
                    ],
                    [
                      {
                        "x": 0.12500000000000003,
                        "y": 0.3125,
                        "z": -0.25,
                        "w": 0.5
                      },
                      {
                        "x": 0.12500000000000003,
                        "y": 0.3125,
                        "z": 0.75,
                        "w": 0.5
                      }
                    ],
                    [
                      {
                        "x": 0.125,
                        "y": 0.18750000000000003,
                        "z": -0.25,
                        "w": 0.5
                      },
                      {
                        "x": 0.125,
                        "y": 0.18750000000000003,
                        "z": 0.75,
                        "w": 0.5
                      }
                    ],
                    [
                      {
                        "x": 0.3125,
                        "y": 0.1875,
                        "z": -0.375,
                        "w": 0.75
                      },
                      {
                        "x": 0.3125,
                        "y": 0.1875,
                        "z": 1.125,
                        "w": 0.75
                      }
                    ],
                    [
                      {
                        "x": 0.49999999999999994,
                        "y": 0.25,
                        "z": -0.5,
                        "w": 1.0
                      },
                      {
                        "x": 0.49999999999999994,
                        "y": 0.25,
                        "z": 1.5,
                        "w": 1.0
                      }
                    ]
                  ]
                }
              },
              "leader": {
                "Polyline": [
                  {
                    "x": 0.5,
                    "y": 0.75,
                    "z": 1.0
                  },
                  {
                    "x": 0.46464466094067247,
                    "y": 0.7474873734152929,
                    "z": 1.0
                  },
                  {
                    "x": 0.4530172966313334,
                    "y": 0.7455455902473328,
                    "z": 1.0
                  },
                  {
                    "x": 0.43,
                    "y": 0.74,
                    "z": 1.0
                  },
                  {
                    "x": 0.35,
                    "y": 0.7,
                    "z": 1.0
                  },
                  {
                    "x": 0.27941176470588236,
                    "y": 0.6176470588235294,
                    "z": 1.0
                  },
                  {
                    "x": 0.25,
                    "y": 0.5,
                    "z": 1.0
                  },
                  {
                    "x": 0.27941176470588236,
                    "y": 0.38235294117647056,
                    "z": 1.0
                  },
                  {
                    "x": 0.3229387068633638,
                    "y": 0.32350790258618,
                    "z": 1.0
                  },
                  {
                    "x": 0.35,
                    "y": 0.3,
                    "z": 1.0
                  },
                  {
                    "x": 0.43,
                    "y": 0.26,
                    "z": 1.0
                  },
                  {
                    "x": 0.45301729663133333,
                    "y": 0.2544544097526668,
                    "z": 1.0
                  },
                  {
                    "x": 0.4646446609406724,
                    "y": 0.25251262658470713,
                    "z": 1.0
                  },
                  {
                    "x": 0.5,
                    "y": 0.25,
                    "z": 1.0
                  }
                ]
              },
              "tol": 0.01
            }
          }
        },
        {
          "vertices": [
            8,
            6
          ],
          "curve": {
            "Line": [
              {
                "x": 0.5,
                "y": 0.75,
                "z": 0.0
              },
              {
                "x": 0.5,
                "y": 0.75,
                "z": 1.0
              }
            ]
          }
        },
        {
          "vertices": [
            8,
            9
          ],
          "curve": {
            "IntersectionCurve": {
              "surface0": {
                "Plane": {
                  "o": {
                    "x": 0.0,
                    "y": 0.0,
                    "z": 0.0
                  },
                  "p": {
                    "x": 1.0,
                    "y": 0.0,
                    "z": 0.0
                  },
                  "q": {
                    "x": 0.0,
                    "y": 1.0,
                    "z": 0.0
                  }
                }
              },
              "surface1": {
                "NURBSSurface": {
                  "knot_vecs": [
                    [
                      0.0,
                      0.0,
                      0.0,
                      0.25,
                      0.5,
                      0.75,
                      1.0,
                      1.0,
                      1.0
                    ],
                    [
                      0.0,
                      0.0,
                      1.0,
                      1.0
                    ]
                  ],
                  "control_points": [
                    [
                      {
                        "x": 0.5,
                        "y": 0.75,
                        "z": -0.5,
                        "w": 1.0
                      },
                      {
                        "x": 0.5,
                        "y": 0.75,
                        "z": 1.5,
                        "w": 1.0
                      }
                    ],
                    [
                      {
                        "x": 0.3125,
                        "y": 0.5625,
                        "z": -0.375,
                        "w": 0.75
                      },
                      {
                        "x": 0.3125,
                        "y": 0.5625,
                        "z": 1.125,
                        "w": 0.75
                      }
                    ],
                    [
                      {
                        "x": 0.12500000000000003,
                        "y": 0.3125,
                        "z": -0.25,
                        "w": 0.5
                      },
                      {
                        "x": 0.12500000000000003,
                        "y": 0.3125,
                        "z": 0.75,
                        "w": 0.5
                      }
                    ],
                    [
                      {
                        "x": 0.125,
                        "y": 0.18750000000000003,
                        "z": -0.25,
                        "w": 0.5
                      },
                      {
                        "x": 0.125,
                        "y": 0.18750000000000003,
                        "z": 0.75,
                        "w": 0.5
                      }
                    ],
                    [
                      {
                        "x": 0.3125,
                        "y": 0.1875,
                        "z": -0.375,
                        "w": 0.75
                      },
                      {
                        "x": 0.3125,
                        "y": 0.1875,
                        "z": 1.125,
                        "w": 0.75
                      }
                    ],
                    [
                      {
                        "x": 0.49999999999999994,
                        "y": 0.25,
                        "z": -0.5,
                        "w": 1.0
                      },
                      {
                        "x": 0.49999999999999994,
                        "y": 0.25,
                        "z": 1.5,
                        "w": 1.0
                      }
                    ]
                  ]
                }
              },
              "leader": {
                "Polyline": [
                  {
                    "x": 0.5,
                    "y": 0.75,
                    "z": 0.0
                  },
                  {
                    "x": 0.46464466094067247,
                    "y": 0.7474873734152929,
                    "z": 0.0
                  },
                  {
                    "x": 0.45301729663133333,
                    "y": 0.7455455902473331,
                    "z": 0.0
                  },
                  {
                    "x": 0.43,
                    "y": 0.74,
                    "z": 0.0
                  },
                  {
                    "x": 0.35,
                    "y": 0.7,
                    "z": 0.0
                  },
                  {
                    "x": 0.2794117647058824,
                    "y": 0.6176470588235294,
                    "z": 0.0
                  },
                  {
                    "x": 0.25,
                    "y": 0.5,
                    "z": 0.0
                  },
                  {
                    "x": 0.27941176470588236,
                    "y": 0.38235294117647056,
                    "z": 0.0
                  },
                  {
                    "x": 0.3229387068633637,
                    "y": 0.32350790258617995,
                    "z": 0.0
                  },
                  {
                    "x": 0.35,
                    "y": 0.3,
                    "z": 0.0
                  },
                  {
                    "x": 0.43,
                    "y": 0.26,
                    "z": 0.0
                  },
                  {
                    "x": 0.45301729663133333,
                    "y": 0.25445440975266687,
                    "z": 0.0
                  },
                  {
                    "x": 0.4646446609406724,
                    "y": 0.25251262658470713,
                    "z": 0.0
                  },
                  {
                    "x": 0.5,
                    "y": 0.25,
                    "z": 0.0
                  }
                ]
              },
              "tol": 0.01
            }
          }
        },
        {
          "vertices": [
            9,
            7
          ],
          "curve": {
            "Line": [
              {
                "x": 0.5,
                "y": 0.25,
                "z": 0.0
              },
              {
                "x": 0.5,
                "y": 0.25,
                "z": 1.0
              }
            ]
          }
        },
        {
          "vertices": [
            8,
            9
          ],
          "curve": {
            "IntersectionCurve": {
              "surface0": {
                "Plane": {
                  "o": {
                    "x": 0.0,
                    "y": 0.0,
                    "z": 0.0
                  },
                  "p": {
                    "x": 1.0,
                    "y": 0.0,
                    "z": 0.0
                  },
                  "q": {
                    "x": 0.0,
                    "y": 1.0,
                    "z": 0.0
                  }
                }
              },
              "surface1": {
                "NURBSSurface": {
                  "knot_vecs": [
                    [
                      0.0,
                      0.0,
                      0.0,
                      0.25,
                      0.5,
                      0.75,
                      1.0,
                      1.0,
                      1.0
                    ],
                    [
                      0.0,
                      0.0,
                      1.0,
                      1.0
                    ]
                  ],
                  "control_points": [
                    [
                      {
                        "x": 0.5,
                        "y": 0.25,
                        "z": -0.5,
                        "w": 1.0
                      },
                      {
                        "x": 0.5,
                        "y": 0.25,
                        "z": 1.5,
                        "w": 1.0
                      }
                    ],
                    [
                      {
                        "x": 0.4375,
                        "y": 0.1875,
                        "z": -0.375,
                        "w": 0.75
                      },
                      {
                        "x": 0.4375,
                        "y": 0.1875,
                        "z": 1.125,
                        "w": 0.75
                      }
                    ],
                    [
                      {
                        "x": 0.375,
                        "y": 0.1875,
                        "z": -0.25,
                        "w": 0.5
                      },
                      {
                        "x": 0.375,
                        "y": 0.1875,
                        "z": 0.75,
                        "w": 0.5
                      }
                    ],
                    [
                      {
                        "x": 0.375,
                        "y": 0.31249999999999994,
                        "z": -0.25,
                        "w": 0.5
                      },
                      {
                        "x": 0.375,
                        "y": 0.31249999999999994,
                        "z": 0.75,
                        "w": 0.5
                      }
                    ],
                    [
                      {
                        "x": 0.4375,
                        "y": 0.5625,
                        "z": -0.375,
                        "w": 0.75
                      },
                      {
                        "x": 0.4375,
                        "y": 0.5625,
                        "z": 1.125,
                        "w": 0.75
                      }
                    ],
                    [
                      {
                        "x": 0.5,
                        "y": 0.75,
                        "z": -0.5,
                        "w": 1.0
                      },
                      {
                        "x": 0.5,
                        "y": 0.75,
                        "z": 1.5,
                        "w": 1.0
                      }
                    ]
                  ]
                }
              },
              "leader": {
                "Polyline": [
                  {
                    "x": 0.5,
                    "y": 0.75,
                    "z": 0.0
                  },
                  {
                    "x": 0.5353553390593275,
                    "y": 0.7474873734152929,
                    "z": 0.0
                  },
                  {
                    "x": 0.5469827033686665,
                    "y": 0.7455455902473329,
                    "z": 0.0
                  },
                  {
                    "x": 0.57,
                    "y": 0.74,
                    "z": 0.0
                  },
                  {
                    "x": 0.65,
                    "y": 0.7,
                    "z": 0.0
                  },
                  {
                    "x": 0.6770612931366364,
                    "y": 0.6764920974138202,
                    "z": 0.0
                  },
                  {
                    "x": 0.7205882352941176,
                    "y": 0.6176470588235293,
                    "z": 0.0
                  },
                  {
                    "x": 0.75,
                    "y": 0.49999999999999994,
                    "z": 0.0
                  },
                  {
                    "x": 0.7205882352941176,
                    "y": 0.38235294117647056,
                    "z": 0.0
                  },
                  {
                    "x": 0.65,
                    "y": 0.3,
                    "z": 0.0
                  },
                  {
                    "x": 0.57,
                    "y": 0.26,
                    "z": 0.0
                  },
                  {
                    "x": 0.5469827033686666,
                    "y": 0.25445440975266687,
                    "z": 0.0
                  },
                  {
                    "x": 0.5353553390593275,
                    "y": 0.2525126265847071,
                    "z": 0.0
                  },
                  {
                    "x": 0.5,
                    "y": 0.25,
                    "z": 0.0
                  }
                ]
              },
              "tol": 0.01
            }
          }
        },
        {
          "vertices": [
            10,
            0
          ],
          "curve": {
            "Line": [
              {
                "x": 0.0,
                "y": 0.0,
                "z": 0.0
              },
              {
                "x": 1.0,
                "y": 0.0,
                "z": 0.0
              }
            ]
          }
        },
        {
          "vertices": [
            11,
            1
          ],
          "curve": {
            "Line": [
              {
                "x": 0.0,
                "y": 1.0,
                "z": 0.0
              },
              {
                "x": 1.0,
                "y": 1.0,
                "z": 0.0
              }
            ]
          }
        },
        {
          "vertices": [
            10,
            11
          ],
          "curve": {
            "Line": [
              {
                "x": 0.0,
                "y": 0.0,
                "z": 0.0
              },
              {
                "x": 0.0,
                "y": 1.0,
                "z": 0.0
              }
            ]
          }
        },
        {
          "vertices": [
            11,
            5
          ],
          "curve": {
            "Line": [
              {
                "x": 0.0,
                "y": 1.0,
                "z": 0.0
              },
              {
                "x": 0.0,
                "y": 1.0,
                "z": 1.0
              }
            ]
          }
        },
        {
          "vertices": [
            10,
            4
          ],
          "curve": {
            "Line": [
              {
                "x": 0.0,
                "y": 0.0,
                "z": 0.0
              },
              {
                "x": 0.0,
                "y": 0.0,
                "z": 1.0
              }
            ]
          }
        }
      ],
      "faces": [
        {
          "boundaries": [
            [
              [
                0,
                true
              ],
              [
                1,
                true
              ],
              [
                2,
                false
              ],
              [
                3,
                false
              ]
            ]
          ],
          "orientation": true,
          "surface": {
            "Plane": {
              "o": {
                "x": 1.0,
                "y": 0.0,
                "z": 0.0
              },
              "p": {
                "x": 1.0,
                "y": 1.0,
                "z": 0.0
              },
              "q": {
                "x": 1.0,
                "y": 0.0,
                "z": 1.0
              }
            }
          }
        },
        {
          "boundaries": [
            [
              [
                4,
                true
              ],
              [
                2,
                true
              ],
              [
                5,
                false
              ],
              [
                6,
                false
              ]
            ],
            [
              [
                7,
                true
              ],
              [
                8,
                false
              ]
            ]
          ],
          "orientation": true,
          "surface": {
            "Plane": {
              "o": {
                "x": 0.0,
                "y": 0.0,
                "z": 1.0
              },
              "p": {
                "x": 1.0,
                "y": 0.0,
                "z": 1.0
              },
              "q": {
                "x": 0.0,
                "y": 1.0,
                "z": 1.0
              }
            }
          }
        },
        {
          "boundaries": [
            [
              [
                9,
                false
              ],
              [
                10,
                true
              ],
              [
                11,
                true
              ],
              [
                8,
                false
              ]
            ]
          ],
          "orientation": false,
          "surface": {
            "NURBSSurface": {
              "knot_vecs": [
                [
                  0.0,
                  0.0,
                  0.0,
                  0.25,
                  0.5,
                  0.75,
                  1.0,
                  1.0,
                  1.0
                ],
                [
                  0.0,
                  0.0,
                  1.0,
                  1.0
                ]
              ],
              "control_points": [
                [
                  {
                    "x": 0.5,
                    "y": 0.75,
                    "z": -0.5,
                    "w": 1.0
                  },
                  {
                    "x": 0.5,
                    "y": 0.75,
                    "z": 1.5,
                    "w": 1.0
                  }
                ],
                [
                  {
                    "x": 0.3125,
                    "y": 0.5625,
                    "z": -0.375,
                    "w": 0.75
                  },
                  {
                    "x": 0.3125,
                    "y": 0.5625,
                    "z": 1.125,
                    "w": 0.75
                  }
                ],
                [
                  {
                    "x": 0.12500000000000003,
                    "y": 0.3125,
                    "z": -0.25,
                    "w": 0.5
                  },
                  {
                    "x": 0.12500000000000003,
                    "y": 0.3125,
                    "z": 0.75,
                    "w": 0.5
                  }
                ],
                [
                  {
                    "x": 0.125,
                    "y": 0.18750000000000003,
                    "z": -0.25,
                    "w": 0.5
                  },
                  {
                    "x": 0.125,
                    "y": 0.18750000000000003,
                    "z": 0.75,
                    "w": 0.5
                  }
                ],
                [
                  {
                    "x": 0.3125,
                    "y": 0.1875,
                    "z": -0.375,
                    "w": 0.75
                  },
                  {
                    "x": 0.3125,
                    "y": 0.1875,
                    "z": 1.125,
                    "w": 0.75
                  }
                ],
                [
                  {
                    "x": 0.49999999999999994,
                    "y": 0.25,
                    "z": -0.5,
                    "w": 1.0
                  },
                  {
                    "x": 0.49999999999999994,
                    "y": 0.25,
                    "z": 1.5,
                    "w": 1.0
                  }
                ]
              ]
            }
          }
        },
        {
          "boundaries": [
            [
              [
                7,
                true
              ],
              [
                11,
                false
              ],
              [
                12,
                false
              ],
              [
                9,
                true
              ]
            ]
          ],
          "orientation": false,
          "surface": {
            "NURBSSurface": {
              "knot_vecs": [
                [
                  0.0,
                  0.0,
                  0.0,
                  0.25,
                  0.5,
                  0.75,
                  1.0,
                  1.0,
                  1.0
                ],
                [
                  0.0,
                  0.0,
                  1.0,
                  1.0
                ]
              ],
              "control_points": [
                [
                  {
                    "x": 0.5,
                    "y": 0.25,
                    "z": -0.5,
                    "w": 1.0
                  },
                  {
                    "x": 0.5,
                    "y": 0.25,
                    "z": 1.5,
                    "w": 1.0
                  }
                ],
                [
                  {
                    "x": 0.4375,
                    "y": 0.1875,
                    "z": -0.375,
                    "w": 0.75
                  },
                  {
                    "x": 0.4375,
                    "y": 0.1875,
                    "z": 1.125,
                    "w": 0.75
                  }
                ],
                [
                  {
                    "x": 0.375,
                    "y": 0.1875,
                    "z": -0.25,
                    "w": 0.5
                  },
                  {
                    "x": 0.375,
                    "y": 0.1875,
                    "z": 0.75,
                    "w": 0.5
                  }
                ],
                [
                  {
                    "x": 0.375,
                    "y": 0.31249999999999994,
                    "z": -0.25,
                    "w": 0.5
                  },
                  {
                    "x": 0.375,
                    "y": 0.31249999999999994,
                    "z": 0.75,
                    "w": 0.5
                  }
                ],
                [
                  {
                    "x": 0.4375,
                    "y": 0.5625,
                    "z": -0.375,
                    "w": 0.75
                  },
                  {
                    "x": 0.4375,
                    "y": 0.5625,
                    "z": 1.125,
                    "w": 0.75
                  }
                ],
                [
                  {
                    "x": 0.5,
                    "y": 0.75,
                    "z": -0.5,
                    "w": 1.0
                  },
                  {
                    "x": 0.5,
                    "y": 0.75,
                    "z": 1.5,
                    "w": 1.0
                  }
                ]
              ]
            }
          }
        },
        {
          "boundaries": [
            [
              [
                13,
                true
              ],
              [
                0,
                true
              ],
              [
                14,
                false
              ],
              [
                15,
                false
              ]
            ],
            [
              [
                12,
                true
              ],
              [
                10,
                false
              ]
            ]
          ],
          "orientation": false,
          "surface": {
            "Plane": {
              "o": {
                "x": 0.0,
                "y": 0.0,
                "z": 0.0
              },
              "p": {
                "x": 1.0,
                "y": 0.0,
                "z": 0.0
              },
              "q": {
                "x": 0.0,
                "y": 1.0,
                "z": 0.0
              }
            }
          }
        },
        {
          "boundaries": [
            [
              [
                16,
                true
              ],
              [
                6,
                false
              ],
              [
                17,
                false
              ],
              [
                15,
                true
              ]
            ]
          ],
          "orientation": false,
          "surface": {
            "Plane": {
              "o": {
                "x": 0.0,
                "y": 0.0,
                "z": 0.0
              },
              "p": {
                "x": 0.0,
                "y": 1.0,
                "z": 0.0
              },
              "q": {
                "x": 0.0,
                "y": 0.0,
                "z": 1.0
              }
            }
          }
        },
        {
          "boundaries": [
            [
              [
                13,
                true
              ],
              [
                3,
                true
              ],
              [
                4,
                false
              ],
              [
                17,
                false
              ]
            ]
          ],
          "orientation": true,
          "surface": {
            "Plane": {
              "o": {
                "x": 0.0,
                "y": 0.0,
                "z": 0.0
              },
              "p": {
                "x": 1.0,
                "y": 0.0,
                "z": 0.0
              },
              "q": {
                "x": 0.0,
                "y": 0.0,
                "z": 1.0
              }
            }
          }
        },
        {
          "boundaries": [
            [
              [
                1,
                true
              ],
              [
                5,
                false
              ],
              [
                16,
                false
              ],
              [
                14,
                true
              ]
            ]
          ],
          "orientation": false,
          "surface": {
            "Plane": {
              "o": {
                "x": 0.0,
                "y": 1.0,
                "z": 0.0
              },
              "p": {
                "x": 1.0,
                "y": 1.0,
                "z": 0.0
              },
              "q": {
                "x": 0.0,
                "y": 1.0,
                "z": 1.0
              }
            }
          }
        }
      ]
    }
  ]
}